puzle_gardener-0.3.0a1.dist-info/DESCRIPTION.rst
puzle_gardener-0.3.0a1.dist-info/METADATA
puzle_gardener-0.3.0a1.dist-info/RECORD
puzle_gardener-0.3.0a1.dist-info/WHEEL
puzle_gardener-0.3.0a1.dist-info/entry_points.txt
puzle_gardener-0.3.0a1.dist-info/metadata.json
puzle_gardener-0.3.0a1.dist-info/top_level.txt
src/__init__.py
src/cli.py
src/core.py
src/requirements.txt
src/abstract_tree/__init__.py
src/abstract_tree/models/__init__.py
src/abstract_tree/models/node.py
src/add/__init__.py
src/add/services/__init__.py
src/add/services/add.py
src/cli/__init__.py
src/cli/services/__init__.py
src/cli/services/generate.py
src/config/__init__.py
src/config/models/__init__.py
src/config/models/field.py
src/config/models/gardener_config.py
src/config/models/project_config.py
src/config/models/seed.py
src/config/prompt_models/__init__.py
src/config/prompt_models/gardener_config.yml
src/config/services/__init__.py
src/config/services/data_fetcher.py
src/config/services/prompt_fetcher.py
src/generation/__init__.py
src/generation/services/__init__.py
src/generation/services/generate.py
src/generation/services/seed_manager.py
src/generation/utils/__init__.py
src/generation/utils/recursive_walker.py
src/repository/__init__.py
src/repository/services/__init__.py
src/repository/services/git_manager.py
