Metadata-Version: 2.0
Name: puzle-gardener
Version: 0.3.0a1
Summary: With Gardener, bootstraping a project has never been so easy !
Home-page: https://gitlab.com/puzle-project/gardener
Author: Cedric Chariere Fiedler
Author-email: chariere.fiedler.cedric@gmail.com
License: GPL
Platform: UNKNOWN
Classifier: Development Status :: 3 - Alpha
Classifier: Intended Audience :: Developers
Classifier: Topic :: Software Development :: Code Generators
Classifier: License :: OSI Approved :: GNU General Public License v3 or later (GPLv3+)
Classifier: Programming Language :: Python :: 3.6
Requires-Python: >=3.6
Requires-Dist: pystache (==0.5.4)
Requires-Dist: click (==6.7)
Requires-Dist: GitPython (==2.1.7)
Requires-Dist: prompt-toolkit (==1.0.15)
Requires-Dist: PyYAML (==3.12)
